src/control_unit.vhd
-- ============================================================
-- File     : control_unit.vhd
-- Project  : 32-bit Single-Cycle MIPS Processor
-- Module   : Main CPU Control Unit
-- Author   : CPEN 315 Group
-- Date     : 2026
-- ============================================================
-- Description:
--   Decodes the 3-bit opcode from each instruction and asserts
--   the appropriate control signals for the datapath.
--
-- Opcode Table (3-bit):
--   000 = R-type  (add, sub, and, or, slt, jr)
--   001 = lw      (load word)
--   010 = sw      (store word)
--   011 = beq     (branch if equal)
--   100 = addi    (add immediate)
--   101 = j       (jump)
--   110 = jal     (jump and link)
--   111 = slti    (set less than immediate)
-- ============================================================

library IEEE;
use IEEE.STD_LOGIC_1164.ALL;

entity Control_Unit is
    port (
        opcode       : in  STD_LOGIC_VECTOR(2 downto 0);  -- Instruction opcode
        reset        : in  STD_LOGIC;                      -- Reset signal

        -- Datapath control outputs
        reg_dst      : out STD_LOGIC_VECTOR(1 downto 0);  -- Dest reg select
        mem_to_reg   : out STD_LOGIC_VECTOR(1 downto 0);  -- Mem/ALU to reg
        alu_op       : out STD_LOGIC_VECTOR(1 downto 0);  -- ALU operation type
        jump         : out STD_LOGIC;                      -- Jump signal
        branch       : out STD_LOGIC;                      -- Branch signal
        mem_read     : out STD_LOGIC;                      -- Memory read enable
        mem_write    : out STD_LOGIC;                      -- Memory write enable
        alu_src      : out STD_LOGIC;                      -- ALU 2nd operand src
        reg_write    : out STD_LOGIC;                      -- Register write enable
        sign_or_zero : out STD_LOGIC                       -- Sign/zero extend
    );
end Control_Unit;

architecture Behavioral of Control_Unit is
begin

    process(reset, opcode)
    begin
        if reset = '1' then
            -- Default: all signals deasserted
            reg_dst      <= "00";
            mem_to_reg   <= "00";
            alu_op       <= "00";
            jump         <= '0';
            branch       <= '0';
            mem_read     <= '0';
            mem_write    <= '0';
            alu_src      <= '0';
            reg_write    <= '0';
            sign_or_zero <= '0';

        else
            case opcode is

                -- -----------------------------------------------
                -- R-type: add, sub, and, or, slt, jr
                -- -----------------------------------------------
                when "000" =>
                    reg_dst      <= "01";  -- rd field selects dest
                    mem_to_reg   <= "00";  -- ALU result to reg
                    alu_op       <= "10";  -- Use funct field
                    jump         <= '0';
                    branch       <= '0';
                    mem_read     <= '0';
                    mem_write    <= '0';
                    alu_src      <= '0';  -- 2nd operand from register
                    reg_write    <= '1';
                    sign_or_zero <= '0';

                -- -----------------------------------------------
                -- lw: load word
                -- -----------------------------------------------
                when "001" =>
                    reg_dst      <= "00";  -- rt field selects dest
                    mem_to_reg   <= "01";  -- Memory data to reg
                    alu_op       <= "00";  -- ADD (compute address)
                    jump         <= '0';
                    branch       <= '0';
                    mem_read     <= '1';
                    mem_write    <= '0';
                    alu_src      <= '1';  -- 2nd operand from immediate
                    reg_write    <= '1';
                    sign_or_zero <= '1';  -- Sign extend immediate

                -- -----------------------------------------------
                -- sw: store word
                -- -----------------------------------------------
                when "010" =>
                    reg_dst      <= "00";
                    mem_to_reg   <= "00";
                    alu_op       <= "00";  -- ADD (compute address)
                    jump         <= '0';
                    branch       <= '0';
                    mem_read     <= '0';
                    mem_write    <= '1';
                    alu_src      <= '1';  -- 2nd operand from immediate
                    reg_write    <= '0';
                    sign_or_zero <= '1';  -- Sign extend immediate

                -- -----------------------------------------------
                -- beq: branch if equal
                -- -----------------------------------------------
                when "011" =>
                    reg_dst      <= "00";
                    mem_to_reg   <= "00";
                    alu_op       <= "01";  -- SUB (compare)
                    jump         <= '0';
                    branch       <= '1';
                    mem_read     <= '0';
                    mem_write    <= '0';
                    alu_src      <= '0';  -- 2nd operand from register
                    reg_write    <= '0';
                    sign_or_zero <= '1';

                -- -----------------------------------------------
                -- addi: add immediate
                -- -----------------------------------------------
                when "100" =>
                    reg_dst      <= "00";  -- rt field selects dest
                    mem_to_reg   <= "00";  -- ALU result to reg
                    alu_op       <= "11";  -- ADD
                    jump         <= '0';
                    branch       <= '0';
                    mem_read     <= '0';
                    mem_write    <= '0';
                    alu_src      <= '1';  -- 2nd operand from immediate
                    reg_write    <= '1';
                    sign_or_zero <= '1';  -- Sign extend

                -- -----------------------------------------------
                -- j: jump
                -- -----------------------------------------------
                when "101" =>
                    reg_dst      <= "00";
                    mem_to_reg   <= "00";
                    alu_op       <= "00";
                    jump         <= '1';
                    branch       <= '0';
                    mem_read     <= '0';
                    mem_write    <= '0';
                    alu_src      <= '0';
                    reg_write    <= '0';
                    sign_or_zero <= '0';

                -- -----------------------------------------------
                -- jal: jump and link
                -- -----------------------------------------------
                when "110" =>
                    reg_dst      <= "10";  -- R7 (return address reg)
                    mem_to_reg   <= "10";  -- PC+4 written to R7
                    alu_op       <= "00";
                    jump         <= '1';
                    branch       <= '0';
                    mem_read     <= '0';
                    mem_write    <= '0';
                    alu_src      <= '0';
                    reg_write    <= '1';  -- Write return addr to R7
                    sign_or_zero <= '0';

                -- -----------------------------------------------
                -- slti: set less than immediate
                -- -----------------------------------------------
                when "111" =>
                    reg_dst      <= "00";  -- rt field selects dest
                    mem_to_reg   <= "00";  -- ALU result to reg
                    alu_op       <= "10";  -- SLT
                    jump         <= '0';
                    branch       <= '0';
                    mem_read     <= '0';
                    mem_write    <= '0';
                    alu_src      <= '1';  -- 2nd operand from immediate
                    reg_write    <= '1';
                    sign_or_zero <= '1';  -- Sign extend

                when others =>
                    reg_dst      <= "00";
                    mem_to_reg   <= "00";
                    alu_op       <= "00";
                    jump         <= '0';
                    branch       <= '0';
                    mem_read     <= '0';
                    mem_write    <= '0';
                    alu_src      <= '0';
                    reg_write    <= '0';
                    sign_or_zero <= '0';

            end case;
        end if;
    end process;

end Behavioral;

testbench/tb_control_unit.vhd
-- ============================================================
-- File     : tb_control_unit.vhd
-- Project  : 32-bit Single-Cycle MIPS Processor
-- Module   : Control Unit Testbench (Task 5)
-- Author   : CPEN 315 Group
-- Date     : 2026
-- ============================================================
-- Task 5: Display control signals for:
--   add (000), slti (111), j (101), jal (110),
--   lw  (001), sw  (010), beq (011), addi (100)
-- ============================================================

library IEEE;
use IEEE.STD_LOGIC_1164.ALL;

entity tb_Control_Unit is
end tb_Control_Unit;

architecture Behavioral of tb_Control_Unit is

    component Control_Unit
        port (
            opcode       : in  STD_LOGIC_VECTOR(2 downto 0);
            reset        : in  STD_LOGIC;
            reg_dst      : out STD_LOGIC_VECTOR(1 downto 0);
            mem_to_reg   : out STD_LOGIC_VECTOR(1 downto 0);
            alu_op       : out STD_LOGIC_VECTOR(1 downto 0);
            jump         : out STD_LOGIC;
            branch       : out STD_LOGIC;
            mem_read     : out STD_LOGIC;
            mem_write    : out STD_LOGIC;
            alu_src      : out STD_LOGIC;
            reg_write    : out STD_LOGIC;
            sign_or_zero : out STD_LOGIC
        );
    end component;

    signal opcode       : STD_LOGIC_VECTOR(2 downto 0) := "000";
    signal reset        : STD_LOGIC := '0';
    signal reg_dst      : STD_LOGIC_VECTOR(1 downto 0);
    signal mem_to_reg   : STD_LOGIC_VECTOR(1 downto 0);
    signal alu_op       : STD_LOGIC_VECTOR(1 downto 0);
    signal jump         : STD_LOGIC;
    signal branch       : STD_LOGIC;
    signal mem_read     : STD_LOGIC;
    signal mem_write    : STD_LOGIC;
    signal alu_src      : STD_LOGIC;
    signal reg_write    : STD_LOGIC;
    signal sign_or_zero : STD_LOGIC;

    -- Helper: convert std_logic_vector to binary string (GHDL-compatible)
    function slv_to_str(slv : std_logic_vector) return string is
        variable result : string(1 to slv'length);
        variable idx    : integer := 1;
    begin
        for i in slv'left downto slv'right loop
            if slv(i) = '1' then
                result(idx) := '1';
            else
                result(idx) := '0';
            end if;
            idx := idx + 1;
        end loop;
        return result;
    end function;

    -- Helper: print all control signals
    procedure print_signals(name : string) is
    begin
        report name & " | reg_dst=" & slv_to_str(reg_dst)
             & " mem_to_reg=" & slv_to_str(mem_to_reg)
             & " alu_op=" & slv_to_str(alu_op)
             & " jump=" & std_logic'image(jump)
             & " branch=" & std_logic'image(branch)
             & " mem_read=" & std_logic'image(mem_read)
             & " mem_write=" & std_logic'image(mem_write)
             & " alu_src=" & std_logic'image(alu_src)
             & " reg_write=" & std_logic'image(reg_write)
             & " sign_or_zero=" & std_logic'image(sign_or_zero);
    end procedure;

begin

    uut: Control_Unit port map (
        opcode       => opcode,
        reset        => reset,
        reg_dst      => reg_dst,
        mem_to_reg   => mem_to_reg,
        alu_op       => alu_op,
        jump         => jump,
        branch       => branch,
        mem_read     => mem_read,
        mem_write    => mem_write,
        alu_src      => alu_src,
        reg_write    => reg_write,
        sign_or_zero => sign_or_zero
    );

    stim_proc: process
    begin
        reset <= '1'; wait for 10 ns;
        reset <= '0'; wait for 10 ns;

        -- Task 5: Display control signals for each instruction

        -- add (R-type, opcode = 000)
        opcode <= "000"; wait for 20 ns;
        print_signals("add  (000)");

        -- slti (opcode = 111)
        opcode <= "111"; wait for 20 ns;
        print_signals("slti (111)");

        -- j (opcode = 101)
        opcode <= "101"; wait for 20 ns;
        print_signals("j    (101)");
        assert jump = '1'
            report "FAIL: j should assert jump=1" severity error;

        -- jal (opcode = 110)
        opcode <= "110"; wait for 20 ns;
        print_signals("jal  (110)");
        assert jump = '1' and reg_write = '1'
            report "FAIL: jal should assert jump=1 and reg_write=1" severity error;

        -- lw (opcode = 001)
        opcode <= "001"; wait for 20 ns;
        print_signals("lw   (001)");
        assert mem_read = '1' and reg_write = '1'
            report "FAIL: lw should assert mem_read=1 and reg_write=1" severity error;

        -- sw (opcode = 010)
        opcode <= "010"; wait for 20 ns;
        print_signals("sw   (010)");
        assert mem_write = '1' and reg_write = '0'
            report "FAIL: sw should assert mem_write=1, reg_write=0" severity error;

        -- beq (opcode = 011)
        opcode <= "011"; wait for 20 ns;
        print_signals("beq  (011)");
        assert branch = '1'
            report "FAIL: beq should assert branch=1" severity error;

        -- addi (opcode = 100)
        opcode <= "100"; wait for 20 ns;
        print_signals("addi (100)");
        assert alu_src = '1' and reg_write = '1'
            report "FAIL: addi should assert alu_src=1 and reg_write=1" severity error;

        report "===== Control Unit Testbench Complete =====";
        std.env.stop;
        wait;
    end process;

end Behavioral;

waveforms/tb_control_unit.vcd
$date
  Wed Apr  1 17:42:50 2026
$end
$version
  GHDL v0
$end
$timescale
  1 fs
$end
$scope module standard $end
$upscope $end
$scope module textio $end
$upscope $end
$scope module std_logic_1164 $end
$upscope $end
$scope module env $end
$upscope $end
$scope module tb_control_unit $end
$var reg 3 ! opcode[2:0] $end
$var reg 1 " reset $end
$var reg 2 # reg_dst[1:0] $end
$var reg 2 $ mem_to_reg[1:0] $end
$var reg 2 % alu_op[1:0] $end
$var reg 1 & jump $end
$var reg 1 ' branch $end
$var reg 1 ( mem_read $end
$var reg 1 ) mem_write $end
$var reg 1 * alu_src $end
$var reg 1 + reg_write $end
$var reg 1 , sign_or_zero $end
$scope module uut $end
$var reg 3 - opcode[2:0] $end
$var reg 1 . reset $end
$var reg 2 / reg_dst[1:0] $end
$var reg 2 0 mem_to_reg[1:0] $end
$var reg 2 1 alu_op[1:0] $end
$var reg 1 2 jump $end
$var reg 1 3 branch $end
$var reg 1 4 mem_read $end
$var reg 1 5 mem_write $end
$var reg 1 6 alu_src $end
$var reg 1 7 reg_write $end
$var reg 1 8 sign_or_zero $end
$upscope $end
$upscope $end
$enddefinitions $end
#0
b000 !
1"
b00 #
b00 $
b00 %
0&
0'
0(
0)
0*
0+
0,
b000 -
1.
b00 /
b00 0
b00 1
02
03
04
05
06
07
08
#10000000
0"
b01 #
b10 %
1+
0.
b01 /
b10 1
17
#40000000
b111 !
b00 #
1*
1,
b111 -
b00 /
16
18
#60000000
b101 !
b00 %
1&
0*
0+
0,
b101 -
b00 1
12
06
07
08
#80000000
b110 !
b10 #
b10 $
1+
b110 -
b10 /
b10 0
17
#100000000
b001 !
b00 #
b01 $
0&
1(
1*
1,
b001 -
b00 /
b01 0
02
14
16
18
#120000000
b010 !
b00 $
0(
1)
0+
b010 -
b00 0
04
15
07
#140000000
b011 !
b01 %
1'
0)
0*
b011 -
b01 1
13
05
06
#160000000
b100 !
b11 %
0'
1*
1+
b100 -
b11 1
03
16
17
