src/data_memory.vhd
-- ============================================================
-- File     : data_memory.vhd
-- Project  : 32-bit Single-Cycle MIPS Processor
-- Module   : Data Memory
-- Author   : CPEN 315 Group
-- Date     : 2026
-- ============================================================
-- Description:
--   256-entry synchronous data memory, each entry 32 bits wide.
--   Write: on rising clock edge when mem_write_en = '1'.
--   Read : synchronous when mem_read = '1', else outputs zero.
-- ============================================================

library IEEE;
use IEEE.STD_LOGIC_1164.ALL;
use IEEE.NUMERIC_STD.ALL;

entity Data_Memory is
    port (
        clk             : in  STD_LOGIC;
        mem_access_addr : in  STD_LOGIC_VECTOR(31 downto 0);  -- Address
        mem_write_data  : in  STD_LOGIC_VECTOR(31 downto 0);  -- Data to write
        mem_write_en    : in  STD_LOGIC;                       -- Write enable
        mem_read        : in  STD_LOGIC;                       -- Read enable
        mem_read_data   : out STD_LOGIC_VECTOR(31 downto 0)   -- Data read out
    );
end Data_Memory;

architecture Behavioral of Data_Memory is

    -- 256 x 32-bit RAM
    type data_mem_type is array(0 to 255) of STD_LOGIC_VECTOR(31 downto 0);
    signal RAM : data_mem_type := (others => x"00000000");

    signal ram_addr : integer range 0 to 255;

begin

    -- Address: use lower 8 bits as index
    ram_addr <= to_integer(unsigned(mem_access_addr(7 downto 0)));

    process(clk)
    begin
        if rising_edge(clk) then
            -- Write operation
            if mem_write_en = '1' then
                RAM(ram_addr) <= mem_write_data;
            end if;

            -- Read operation
            if mem_read = '1' then
                mem_read_data <= RAM(ram_addr);
            else
                mem_read_data <= x"00000000";
            end if;
        end if;
    end process;

end Behavioral;

testbench/tb_data_memory.vhd
-- ============================================================
-- File     : tb_data_memory.vhd
-- Project  : 32-bit Single-Cycle MIPS Processor
-- Module   : Data Memory Testbench (Task 1)
-- Author   : CPEN 315 Group
-- Date     : 2026
-- ============================================================
-- Task 1 Test Cases:
--   i.  Write 1024    to address 2,  then read it back
--   ii. Write 429496  to address 4,  then read it back
-- ============================================================

library IEEE;
use IEEE.STD_LOGIC_1164.ALL;
use IEEE.NUMERIC_STD.ALL;

entity tb_Data_Memory is
end tb_Data_Memory;

architecture Behavioral of tb_Data_Memory is

    component Data_Memory
        port (
            clk             : in  STD_LOGIC;
            mem_access_addr : in  STD_LOGIC_VECTOR(31 downto 0);
            mem_write_data  : in  STD_LOGIC_VECTOR(31 downto 0);
            mem_write_en    : in  STD_LOGIC;
            mem_read        : in  STD_LOGIC;
            mem_read_data   : out STD_LOGIC_VECTOR(31 downto 0)
        );
    end component;

    signal clk             : STD_LOGIC := '0';
    signal mem_access_addr : STD_LOGIC_VECTOR(31 downto 0) := (others => '0');
    signal mem_write_data  : STD_LOGIC_VECTOR(31 downto 0) := (others => '0');
    signal mem_write_en    : STD_LOGIC := '0';
    signal mem_read        : STD_LOGIC := '0';
    signal mem_read_data   : STD_LOGIC_VECTOR(31 downto 0);

    constant CLK_PERIOD : time := 10 ns;

begin

    uut: Data_Memory port map (
        clk             => clk,
        mem_access_addr => mem_access_addr,
        mem_write_data  => mem_write_data,
        mem_write_en    => mem_write_en,
        mem_read        => mem_read,
        mem_read_data   => mem_read_data
    );

    -- Clock generation
    clk_proc: process
    begin
        clk <= '0'; wait for CLK_PERIOD/2;
        clk <= '1'; wait for CLK_PERIOD/2;
    end process;

    stim_proc: process
    begin
        wait for CLK_PERIOD;

        -- -------------------------------------------------------
        -- Task 1.i : Write 1024 to address 2
        -- -------------------------------------------------------
        mem_access_addr <= STD_LOGIC_VECTOR(to_unsigned(2, 32));
        mem_write_data  <= STD_LOGIC_VECTOR(to_unsigned(1024, 32));
        mem_write_en    <= '1';
        mem_read        <= '0';
        wait for CLK_PERIOD;

        -- Read back from address 2
        mem_write_en    <= '0';
        mem_read        <= '1';
        wait for CLK_PERIOD;
        assert mem_read_data = STD_LOGIC_VECTOR(to_unsigned(1024, 32))
            report "FAIL Task1.i: Expected 1024 at address 2" severity error;
        report "Task1.i READ addr 2: data = " & integer'image(to_integer(unsigned(mem_read_data)));
        mem_read <= '0';

        wait for CLK_PERIOD;

        -- -------------------------------------------------------
        -- Task 1.ii : Write 429496 to address 4
        -- -------------------------------------------------------
        mem_access_addr <= STD_LOGIC_VECTOR(to_unsigned(4, 32));
        mem_write_data  <= STD_LOGIC_VECTOR(to_unsigned(429496, 32));
        mem_write_en    <= '1';
        mem_read        <= '0';
        wait for CLK_PERIOD;

        -- Read back from address 4
        mem_write_en    <= '0';
        mem_read        <= '1';
        wait for CLK_PERIOD;
        assert mem_read_data = STD_LOGIC_VECTOR(to_unsigned(429496, 32))
            report "FAIL Task1.ii: Expected 429496 at address 4" severity error;
        report "Task1.ii READ addr 4: data = " & integer'image(to_integer(unsigned(mem_read_data)));
        mem_read <= '0';

        -- -------------------------------------------------------
        -- Verify address 2 still holds 1024 (no corruption)
        -- -------------------------------------------------------
        wait for CLK_PERIOD;
        mem_access_addr <= STD_LOGIC_VECTOR(to_unsigned(2, 32));
        mem_read        <= '1';
        wait for CLK_PERIOD;
        assert mem_read_data = STD_LOGIC_VECTOR(to_unsigned(1024, 32))
            report "FAIL: Address 2 corrupted after writing to address 4" severity error;
        report "Retention check addr 2: data = " & integer'image(to_integer(unsigned(mem_read_data)));

        report "===== Data Memory Testbench Complete =====";
        std.env.stop;
        wait;
    end process;

end Behavioral;

waveforms/tb_data_memory.vcd
$date
  Wed Apr  1 17:42:48 2026
$end
$version
  GHDL v0
$end
$timescale
  1 fs
$end
$scope module standard $end
$upscope $end
$scope module textio $end
$upscope $end
$scope module std_logic_1164 $end
$upscope $end
$scope module numeric_std $end
$upscope $end
$scope module env $end
$upscope $end
$scope module tb_data_memory $end
$var reg 1 ! clk $end
$var reg 32 " mem_access_addr[31:0] $end
$var reg 32 # mem_write_data[31:0] $end
$var reg 1 $ mem_write_en $end
$var reg 1 % mem_read $end
$var reg 32 & mem_read_data[31:0] $end
$scope module uut $end
$var reg 1 ' clk $end
$var reg 32 ( mem_access_addr[31:0] $end
$var reg 32 ) mem_write_data[31:0] $end
$var reg 1 * mem_write_en $end
$var reg 1 + mem_read $end
$var reg 32 , mem_read_data[31:0] $end
$comment ram is not handled $end
$var integer 32 - ram_addr $end
$upscope $end
$upscope $end
$enddefinitions $end
#0
0!
b00000000000000000000000000000000 "
b00000000000000000000000000000000 #
0$
0%
bUUUUUUUUUUUUUUUUUUUUUUUUUUUUUUUU &
0'
b00000000000000000000000000000000 (
b00000000000000000000000000000000 )
0*
0+
bUUUUUUUUUUUUUUUUUUUUUUUUUUUUUUUU ,
b0 -
#5000000
1!
b00000000000000000000000000000000 &
1'
b00000000000000000000000000000000 ,
#10000000
0!
b00000000000000000000000000000010 "
b00000000000000000000010000000000 #
1$
0'
b00000000000000000000000000000010 (
b00000000000000000000010000000000 )
1*
b10 -
#15000000
1!
1'
#20000000
0!
0$
1%
0'
0*
1+
#25000000
1!
b00000000000000000000010000000000 &
1'
b00000000000000000000010000000000 ,
#30000000
0!
0%
0'
0+
#35000000
1!
b00000000000000000000000000000000 &
1'
b00000000000000000000000000000000 ,
#40000000
0!
b00000000000000000000000000000100 "
b00000000000001101000110110111000 #
1$
0'
b00000000000000000000000000000100 (
b00000000000001101000110110111000 )
1*
b100 -
#45000000
1!
1'
#50000000
0!
0$
1%
0'
0*
1+
#55000000
1!
b00000000000001101000110110111000 &
1'
b00000000000001101000110110111000 ,
#60000000
0!
0%
0'
0+
#65000000
1!
b00000000000000000000000000000000 &
1'
b00000000000000000000000000000000 ,
#70000000
0!
b00000000000000000000000000000010 "
1%
0'
b00000000000000000000000000000010 (
1+
b10 -
#75000000
1!
b00000000000000000000010000000000 &
1'
b00000000000000000000010000000000 ,
