src/register_file.vhd
-- ============================================================
-- File     : register_file.vhd
-- Project  : 32-bit Single-Cycle MIPS Processor
-- Module   : Register File (8 x 32-bit registers)
-- Author   : CPEN 315 Group
-- Date     : 2026
-- ============================================================
-- Description:
--   8 general-purpose 32-bit registers (R0..R7).
--   R0 is hardwired to 0x00000000 (read always returns 0).
--   Dual read ports (async), single write port (sync on clk rise).
--   Reset initialises registers with default values.
-- ============================================================

library IEEE;
use IEEE.STD_LOGIC_1164.ALL;
use IEEE.NUMERIC_STD.ALL;

entity Register_File is
    port (
        clk              : in  STD_LOGIC;
        rst              : in  STD_LOGIC;
        reg_write_en     : in  STD_LOGIC;                       -- Write enable
        reg_write_dest   : in  STD_LOGIC_VECTOR(2 downto 0);   -- Dest register addr
        reg_write_data   : in  STD_LOGIC_VECTOR(31 downto 0);  -- Data to write
        reg_read_addr_1  : in  STD_LOGIC_VECTOR(2 downto 0);   -- Read port 1 addr
        reg_read_addr_2  : in  STD_LOGIC_VECTOR(2 downto 0);   -- Read port 2 addr
        reg_read_data_1  : out STD_LOGIC_VECTOR(31 downto 0);  -- Read port 1 data
        reg_read_data_2  : out STD_LOGIC_VECTOR(31 downto 0)   -- Read port 2 data
    );
end Register_File;

architecture Behavioral of Register_File is

    type reg_file_type is array(0 to 7) of STD_LOGIC_VECTOR(31 downto 0);
    signal reg_file : reg_file_type;

begin

    -- Synchronous write + reset
    process(clk, rst)
    begin
        if rst = '1' then
            -- Initialize registers with default values on reset
            reg_file(0) <= x"00000000";  -- R0 always 0
            reg_file(1) <= x"00000001";
            reg_file(2) <= x"00000002";
            reg_file(3) <= x"00000003";
            reg_file(4) <= x"00000004";
            reg_file(5) <= x"00000005";
            reg_file(6) <= x"00000006";
            reg_file(7) <= x"00000007";

        elsif rising_edge(clk) then
            -- Write to register (R0 is read-only, skip write if dest = 0)
            if reg_write_en = '1' and reg_write_dest /= "000" then
                reg_file(to_integer(unsigned(reg_write_dest))) <= reg_write_data;
            end if;
        end if;
    end process;

    -- Asynchronous dual read ports
    -- R0 always reads as 0
    reg_read_data_1 <= x"00000000" when reg_read_addr_1 = "000"
                       else reg_file(to_integer(unsigned(reg_read_addr_1)));

    reg_read_data_2 <= x"00000000" when reg_read_addr_2 = "000"
                       else reg_file(to_integer(unsigned(reg_read_addr_2)));

end Behavioral;

testbench/tb_register_file.vhd
-- ============================================================
-- File     : tb_register_file.vhd
-- Project  : 32-bit Single-Cycle MIPS Processor
-- Module   : Register File Testbench (Task 3)
-- Author   : CPEN 315 Group
-- Date     : 2026
-- ============================================================
-- Task 3 Test Cases:
--   Write and read:
--     Register 1: 1934858
--     Register 3: 8558447
--     Register 5: 203848544
--     Register 7: 20670420
-- ============================================================

library IEEE;
use IEEE.STD_LOGIC_1164.ALL;
use IEEE.NUMERIC_STD.ALL;

entity tb_Register_File is
end tb_Register_File;

architecture Behavioral of tb_Register_File is

    component Register_File
        port (
            clk              : in  STD_LOGIC;
            rst              : in  STD_LOGIC;
            reg_write_en     : in  STD_LOGIC;
            reg_write_dest   : in  STD_LOGIC_VECTOR(2 downto 0);
            reg_write_data   : in  STD_LOGIC_VECTOR(31 downto 0);
            reg_read_addr_1  : in  STD_LOGIC_VECTOR(2 downto 0);
            reg_read_addr_2  : in  STD_LOGIC_VECTOR(2 downto 0);
            reg_read_data_1  : out STD_LOGIC_VECTOR(31 downto 0);
            reg_read_data_2  : out STD_LOGIC_VECTOR(31 downto 0)
        );
    end component;

    signal clk              : STD_LOGIC := '0';
    signal rst              : STD_LOGIC := '0';
    signal reg_write_en     : STD_LOGIC := '0';
    signal reg_write_dest   : STD_LOGIC_VECTOR(2 downto 0) := "000";
    signal reg_write_data   : STD_LOGIC_VECTOR(31 downto 0) := (others => '0');
    signal reg_read_addr_1  : STD_LOGIC_VECTOR(2 downto 0) := "000";
    signal reg_read_addr_2  : STD_LOGIC_VECTOR(2 downto 0) := "000";
    signal reg_read_data_1  : STD_LOGIC_VECTOR(31 downto 0);
    signal reg_read_data_2  : STD_LOGIC_VECTOR(31 downto 0);

    constant CLK_PERIOD : time := 10 ns;

begin

    uut: Register_File port map (
        clk              => clk,
        rst              => rst,
        reg_write_en     => reg_write_en,
        reg_write_dest   => reg_write_dest,
        reg_write_data   => reg_write_data,
        reg_read_addr_1  => reg_read_addr_1,
        reg_read_addr_2  => reg_read_addr_2,
        reg_read_data_1  => reg_read_data_1,
        reg_read_data_2  => reg_read_data_2
    );

    clk_proc: process
    begin
        clk <= '0'; wait for CLK_PERIOD/2;
        clk <= '1'; wait for CLK_PERIOD/2;
    end process;

    stim_proc: process
    begin
        -- Reset
        rst <= '1'; wait for CLK_PERIOD;
        rst <= '0'; wait for CLK_PERIOD;

        -- -------------------------------------------------------
        -- Task 3.i : Write values to registers 1, 3, 5, 7
        -- -------------------------------------------------------

        -- Write 1934858 to Register 1
        reg_write_dest <= "001";
        reg_write_data <= STD_LOGIC_VECTOR(to_unsigned(1934858, 32));
        reg_write_en   <= '1';
        wait for CLK_PERIOD;

        -- Write 8558447 to Register 3
        reg_write_dest <= "011";
        reg_write_data <= STD_LOGIC_VECTOR(to_unsigned(8558447, 32));
        wait for CLK_PERIOD;

        -- Write 203848544 to Register 5
        reg_write_dest <= "101";
        reg_write_data <= STD_LOGIC_VECTOR(to_unsigned(203848544, 32));
        wait for CLK_PERIOD;

        -- Write 20670420 to Register 7
        reg_write_dest <= "111";
        reg_write_data <= STD_LOGIC_VECTOR(to_unsigned(20670420, 32));
        wait for CLK_PERIOD;

        reg_write_en <= '0';
        wait for CLK_PERIOD;

        -- -------------------------------------------------------
        -- Task 3.ii : Read values back from registers 1, 3, 5, 7
        -- -------------------------------------------------------

        -- Read Register 1 and Register 3 simultaneously
        reg_read_addr_1 <= "001";
        reg_read_addr_2 <= "011";
        wait for 5 ns;  -- combinational read, small delay
        assert reg_read_data_1 = STD_LOGIC_VECTOR(to_unsigned(1934858, 32))
            report "FAIL Task3: Register 1 should be 1934858" severity error;
        assert reg_read_data_2 = STD_LOGIC_VECTOR(to_unsigned(8558447, 32))
            report "FAIL Task3: Register 3 should be 8558447" severity error;
        report "Task3 R1: " & integer'image(to_integer(unsigned(reg_read_data_1)));
        report "Task3 R3: " & integer'image(to_integer(unsigned(reg_read_data_2)));

        -- Read Register 5 and Register 7
        reg_read_addr_1 <= "101";
        reg_read_addr_2 <= "111";
        wait for 5 ns;
        assert reg_read_data_1 = STD_LOGIC_VECTOR(to_unsigned(203848544, 32))
            report "FAIL Task3: Register 5 should be 203848544" severity error;
        assert reg_read_data_2 = STD_LOGIC_VECTOR(to_unsigned(20670420, 32))
            report "FAIL Task3: Register 7 should be 20670420" severity error;
        report "Task3 R5: " & integer'image(to_integer(unsigned(reg_read_data_1)));
        report "Task3 R7: " & integer'image(to_integer(unsigned(reg_read_data_2)));

        -- R0 must always read as 0
        reg_read_addr_1 <= "000";
        wait for 5 ns;
        assert reg_read_data_1 = x"00000000"
            report "FAIL: R0 should always read as 0" severity error;
        report "R0 hardwired zero check: " & integer'image(to_integer(unsigned(reg_read_data_1)));

        report "===== Register File Testbench Complete =====";
        std.env.stop;
        wait;
    end process;

end Behavioral;

waveforms/tb_register_file.vcd
$date
  Wed Apr  1 17:42:49 2026
$end
$version
  GHDL v0
$end
$timescale
  1 fs
$end
$scope module standard $end
$upscope $end
$scope module textio $end
$upscope $end
$scope module std_logic_1164 $end
$upscope $end
$scope module numeric_std $end
$upscope $end
$scope module env $end
$upscope $end
$scope module tb_register_file $end
$var reg 1 ! clk $end
$var reg 1 " rst $end
$var reg 1 # reg_write_en $end
$var reg 3 $ reg_write_dest[2:0] $end
$var reg 32 % reg_write_data[31:0] $end
$var reg 3 & reg_read_addr_1[2:0] $end
$var reg 3 ' reg_read_addr_2[2:0] $end
$var reg 32 ( reg_read_data_1[31:0] $end
$var reg 32 ) reg_read_data_2[31:0] $end
$scope module uut $end
$var reg 1 * clk $end
$var reg 1 + rst $end
$var reg 1 , reg_write_en $end
$var reg 3 - reg_write_dest[2:0] $end
$var reg 32 . reg_write_data[31:0] $end
$var reg 3 / reg_read_addr_1[2:0] $end
$var reg 3 0 reg_read_addr_2[2:0] $end
$var reg 32 1 reg_read_data_1[31:0] $end
$var reg 32 2 reg_read_data_2[31:0] $end
$comment reg_file is not handled $end
$upscope $end
$upscope $end
$enddefinitions $end
#0
0!
1"
0#
b000 $
b00000000000000000000000000000000 %
b000 &
b000 '
b00000000000000000000000000000000 (
b00000000000000000000000000000000 )
0*
1+
0,
b000 -
b00000000000000000000000000000000 .
b000 /
b000 0
b00000000000000000000000000000000 1
b00000000000000000000000000000000 2
#5000000
1!
1*
#10000000
0!
0"
0*
0+
#15000000
1!
1*
#20000000
0!
1#
b001 $
b00000000000111011000011000001010 %
0*
1,
b001 -
b00000000000111011000011000001010 .
#25000000
1!
1*
#30000000
0!
b011 $
b00000000100000101001011101101111 %
0*
b011 -
b00000000100000101001011101101111 .
#35000000
1!
1*
#40000000
0!
b101 $
b00001100001001100111101101100000 %
0*
b101 -
b00001100001001100111101101100000 .
#45000000
1!
1*
#50000000
0!
b111 $
b00000001001110110110011111010100 %
0*
b111 -
b00000001001110110110011111010100 .
#55000000
1!
1*
#60000000
0!
0#
0*
0,
#65000000
1!
1*
#70000000
0!
b001 &
b011 '
b00000000000111011000011000001010 (
b00000000100000101001011101101111 )
0*
b001 /
b011 0
b00000000000111011000011000001010 1
b00000000100000101001011101101111 2
#75000000
1!
b101 &
b111 '
b00001100001001100111101101100000 (
b00000001001110110110011111010100 )
1*
b101 /
b111 0
b00001100001001100111101101100000 1
b00000001001110110110011111010100 2
#80000000
0!
b000 &
b00000000000000000000000000000000 (
0*
b000 /
b00000000000000000000000000000000 1
